{
  "receiver": "ca-wechat",
  "status": "firing",
  "alerts": [
    {
      "status": "firing",
      "labels": {
        "alertname": "ERROR-LOG",
        "app": "ngtrade-app-order-admin",
        "app_kubernetes_io_managed_by": "Helm",
        "instance": "10.192.4.135:81",
        "level": "error",
        "project": "ca",
        "severity": "严重"
      },
      "annotations": {
        "description": "ngtrade-app-order-admin",
        "summary": "Error logged.."
      },
      "startsAt": "2025-01-04T10:46:17.546519462Z",
      "endsAt": "0001-01-01T00:00:00Z",
      "generatorURL": "http://monitor-prometheus-67c4fdc6b6-tf4zt:9090/graph?g0.expr=rate%28logback_events_total%7Blevel%3D%22error%22%7D%5B1m%5D%29+%3E+0&g0.tab=1"
    }
  ],
  "groupLabels": {
    "project": "ca"
  },
  "commonLabels": {
    "alertname": "ERROR-LOG",
    "app": "ngtrade-app-order-admin",
    "app_kubernetes_io_managed_by": "Helm",
    "instance": "10.192.4.135:81",
    "level": "error",
    "project": "ca",
    "severity": "严重"
  },
  "commonAnnotations": {
    "description": "ngtrade-app-order-admin",
    "summary": "Error logged.."
  },
  "externalURL": "http://monitor-alert-manager-cb4ccc454-f9n7f:9093",
  "version": "4"
}